optimizr/__init__.py
optimizr/groups.py
optimizr/optimizr.py
optimizr/results.py
optimizr-1.4.7.dist-info/LICENSE
optimizr-1.4.7.dist-info/METADATA
optimizr-1.4.7.dist-info/WHEEL
optimizr-1.4.7.dist-info/top_level.txt
optimizr-1.4.7.dist-info/RECORD
