Metadata-Version: 2.1
Name: optimizr
Version: 1.4.7
Summary: A small package to find similar collections.
Home-page: https://github.com/joeriddles/optimizr
Author: Joseph Riddle, Clayton Gravatt
Author-email: joeriddles10@gmail.com
License: UNKNOWN
Platform: UNKNOWN
Classifier: Programming Language :: Python :: 3
Classifier: License :: OSI Approved :: BSD License
Classifier: Operating System :: OS Independent
Requires-Python: >=3.6
